{"name":"Ember.js","slug":"ember.js","counter":20100}
{"name":"React.js","slug":"react.js","counter":26441}
{"name":"Redux","slug":"redux","counter":3892}
{"name":"Spring Boot","slug":"spring-boot","counter":13791}
{"name":"Butterknife","slug":"butterknife","counter":258}
{"name":"Dagger","slug":"dagger","counter":488}
{"name":"Dapper","slug":"dapper","counter":1433}
{"name":"Elixir","slug":"elixir","counter":2938}
{"name":"Enzyme","slug":"enzyme","counter":208}
{"name":"Immutable.js","slug":"immutable.js","counter":467}
{"name":"Phoenix","slug":"phoenix","counter":351}
{"name":"Quick and Nimble","slug":"quick-nimble","counter":11}
{"name":"React Native","slug":"react-native","counter":8260}
{"name":"Robolectric","slug":"robolectric","counter":1139}
{"name":"Aurelia","slug":"aurelia","counter":1523}
{"name":"ECMAScript 2017","slug":"ecmascript-2017","counter":16}
{"name":"Elm","slug":"elm","counter":658}
{"name":"GraphQL","slug":"graphql","counter":550}
{"name":"JuMP","slug":"jump","counter":0}
{"name":"Physical Web","slug":"physical-web","counter":0}
{"name":"Rapidoid","slug":"rapidoid","counter":0}
{"name":"Recharts","slug":"recharts","counter":0}
{"name":"ReSwift","slug":"reswift","counter":0}
{"name":"Three.js","slug":"three.js","counter":9665}
{"name":"Vue.js","slug":"vue.js","counter":2391}
{"name":"WebRTC","slug":"webrtc","counter":3275}
{"name":"AngularJS","slug":"angularjs","counter":206342}
{"name":"JSPatch","slug":"jspatch","counter":0}
